ca_certificates/__init__.py
require_relative-0.0.0.dist-info/METADATA
require_relative-0.0.0.dist-info/WHEEL
require_relative-0.0.0.dist-info/top_level.txt
require_relative-0.0.0.dist-info/RECORD
