Metadata-Version: 2.4
Name: require_relative
Version: 0.0.0
Summary: Dummy require_relative package for PyPI
Author-email: Your Name <you@example.com>
Requires-Python: >=3.7
